island/__init__.py
island/actions.py
island/bin_island.py
island/commands.py
island/config.py
island/env.py
island/host.py
island/link_config.py
island/manifest.py
island/multiprocess.py
island/repo_config.py
island/tools.py
island/actions/islandAction_checkout.py
island/actions/islandAction_command.py
island/actions/islandAction_commit.py
island/actions/islandAction_deliver-push.py
island/actions/islandAction_deliver.py
island/actions/islandAction_fetch.py
island/actions/islandAction_init.py
island/actions/islandAction_manifest-checkout.py
island/actions/islandAction_manifest-deliver-push.py
island/actions/islandAction_manifest-deliver.py
island/actions/islandAction_manifest-status.py
island/actions/islandAction_manifest-sync.py
island/actions/islandAction_push.py
island/actions/islandAction_status.py
island/actions/islandAction_sync-local.py
island/actions/islandAction_sync.py
island/actions/islandAction_volatile-add.py
island/actions/islandAction_volatile-list.py
island/actions/status.py
island/actions/update_links.py
island-1.3.1.dist-info/LICENSE.txt
island-1.3.1.dist-info/METADATA
island-1.3.1.dist-info/WHEEL
island-1.3.1.dist-info/entry_points.txt
island-1.3.1.dist-info/top_level.txt
island-1.3.1.dist-info/RECORD
