Metadata-Version: 2.2
Name: island
Version: 1.3.1
Summary: island generic source manager (like repo in simple mode)
Author-email: Edouard DUPIN <yui.heero@gmail.com>
License: MPL-2
Project-URL: Homepage, http://github.com/HeeroYui/island
Project-URL: Bug Reports, http://github.com/HeeroYui/island/issues
Project-URL: Source, http://github.com/HeeroYui/island
Keywords: source,manager,repo,qisrc,lutin
Classifier: Development Status :: 2 - Pre-Alpha
Classifier: License :: OSI Approved :: Mozilla Public License 2.0 (MPL 2.0)
Classifier: Programming Language :: Python
Classifier: Topic :: Software Development :: Build Tools
Requires-Python: >=3.7
License-File: LICENSE.txt
Requires-Dist: lxml
Requires-Dist: realog
Requires-Dist: death
Requires-Dist: PyYAML
